sunweather/__init__.py
sunweather/__main__.py
sunweather-1.2.2.dist-info/entry_points.txt
sunweather-1.2.2.dist-info/METADATA
sunweather-1.2.2.dist-info/WHEEL
sunweather-1.2.2.dist-info/RECORD
