Metadata-Version: 2.3
Name: sunweather
Version: 1.2.2
Summary: 
Author: DJ Stomp
Author-email: 85457381+DJStompZone@users.noreply.github.com
Requires-Python: >=3.12
Classifier: Programming Language :: Python :: 3
Classifier: Programming Language :: Python :: 3.12
Classifier: Programming Language :: Python :: 3.13
Requires-Dist: ffmpeg (>=1.4,<2.0)
Requires-Dist: httpx[http2] (>=0.28.1,<0.29.0)
Requires-Dist: numpy (>=2.3.1,<3.0.0)
Requires-Dist: pillow (>=11.3.0,<12.0.0)
Requires-Dist: tqdm (>=4.67.1,<5.0.0)
